{
  "ControlStates": {
    "ContainerComponent": {
      "AllowAccessToGlobals": false,
      "ControlPropertyState": [
        "Fill",
        {
          "AFDDataSourceName": "",
          "AutoRuleBindingEnabled": false,
          "AutoRuleBindingString": "",
          "InvariantPropertyName": "Height",
          "IsLockable": false,
          "NameMapSourceSchema": "?"
        },
        {
          "AFDDataSourceName": "",
          "AutoRuleBindingEnabled": false,
          "AutoRuleBindingString": "",
          "InvariantPropertyName": "Width",
          "IsLockable": false,
          "NameMapSourceSchema": "?"
        },
        "X",
        "Y",
        "ZIndex",
        {
          "AFDDataSourceName": "",
          "AutoRuleBindingEnabled": false,
          "AutoRuleBindingString": "{\r\n    BorderRadius: 8,\r\n    VerticalGap: 10,\r\n    SpacingBetweenContainers: 15,\r\n    PaddingLeft: 2, \r\n    PaddingRight: 2,\r\n    PaddingBottom: 2,\r\n    PaddingTop: 2,\r\n}",
          "InvariantPropertyName": "SubContainer",
          "IsLockable": false,
          "NameMapSourceSchema": "?"
        },
        {
          "AFDDataSourceName": "",
          "AutoRuleBindingEnabled": false,
          "AutoRuleBindingString": "{\n    PaddingLeft: 2,\n    PaddingRight: 2,\n    PaddingBottom: 2,\n    PaddingTop: 2,\n    VerticalGap: 10,\n    SpacingBetweenContainers: 15,\n}",
          "InvariantPropertyName": "EmbeddedCanvasApp",
          "IsLockable": false,
          "NameMapSourceSchema": "?"
        },
        {
          "AFDDataSourceName": "",
          "AutoRuleBindingEnabled": false,
          "AutoRuleBindingString": "{\n    BorderRadius: 8,\n    VerticalGap: 10,\n    SpacingBetweenContainers: 15\n}",
          "InvariantPropertyName": "CustomPage",
          "IsLockable": false,
          "NameMapSourceSchema": "?"
        }
      ],
      "IsAutoGenerated": false,
      "IsComponentDefinition": true,
      "IsDataControl": false,
      "IsFromScreenLayout": false,
      "IsGroupControl": false,
      "IsLocked": false,
      "LayoutName": "",
      "MetaDataIDKey": "",
      "Name": "ContainerComponent",
      "OptimizeForDevices": "Off",
      "ParentIndex": 0,
      "PersistMetaDataIDKey": false,
      "Properties": [
        {
          "Category": "Data",
          "PropertyName": "SubContainer",
          "RuleProviderType": "System"
        },
        {
          "Category": "Data",
          "PropertyName": "EmbeddedCanvasApp",
          "RuleProviderType": "System"
        },
        {
          "Category": "Data",
          "PropertyName": "CustomPage",
          "RuleProviderType": "System"
        },
        {
          "Category": "Design",
          "PropertyName": "ZIndex",
          "RuleProviderType": "Unknown"
        },
        {
          "Category": "Design",
          "PropertyName": "Y",
          "RuleProviderType": "Unknown"
        },
        {
          "Category": "Design",
          "PropertyName": "X",
          "RuleProviderType": "Unknown"
        },
        {
          "Category": "Design",
          "PropertyName": "Width",
          "RuleProviderType": "Unknown"
        },
        {
          "Category": "Design",
          "PropertyName": "Height",
          "RuleProviderType": "Unknown"
        },
        {
          "Category": "Design",
          "PropertyName": "Fill",
          "RuleProviderType": "System"
        }
      ],
      "StyleName": "",
      "Type": "ControlInfo"
    }
  },
  "TopParentName": "ContainerComponent"
}